pyams_auth_oauth/__init__.py
pyams_auth_oauth/include.py
pyams_auth_oauth/interfaces.py
pyams_auth_oauth/plugin.py
pyams_auth_oauth/doctests/README.rst
pyams_auth_oauth/locales/pyams_auth_oauth.pot
pyams_auth_oauth/locales/fr/LC_MESSAGES/pyams_auth_oauth.mo
pyams_auth_oauth/locales/fr/LC_MESSAGES/pyams_auth_oauth.po
pyams_auth_oauth/skin/__init__.py
pyams_auth_oauth/skin/templates/login-providers.pt
pyams_auth_oauth/tests/__init__.py
pyams_auth_oauth/tests/test_utilsdocs.py
pyams_auth_oauth/tests/test_utilsdocstrings.py
pyams_auth_oauth/zmi/__init__.py
pyams_auth_oauth/zmi/folder.py
pyams_auth_oauth/zmi/interfaces.py
pyams_auth_oauth/zmi/plugin.py
pyams_auth_oauth/zmi/provider.py
pyams_auth_oauth-2.1.3.dist-info/LICENSE
pyams_auth_oauth-2.1.3.dist-info/METADATA
pyams_auth_oauth-2.1.3.dist-info/WHEEL
pyams_auth_oauth-2.1.3.dist-info/namespace_packages.txt
pyams_auth_oauth-2.1.3.dist-info/top_level.txt
pyams_auth_oauth-2.1.3.dist-info/RECORD
