Metadata-Version: 2.1
Name: pyams-auth-oauth
Version: 2.1.3
Summary: PyAMS security plug-in for OAuth authentication
Home-page: https://pyams.readthedocs.io
Author: Thierry Florac
Author-email: tflorac@ulthar.net
License: ZPL
Keywords: Pyramid PyAMS
Classifier: License :: OSI Approved :: Zope Public License
Classifier: Development Status :: 4 - Beta
Classifier: Programming Language :: Python
Classifier: Framework :: Pyramid
Classifier: Topic :: Software Development :: Libraries :: Python Modules
License-File: LICENSE
Requires-Dist: setuptools
Requires-Dist: authomatic >=1.2.0
Requires-Dist: persistent
Requires-Dist: pyams-form
Requires-Dist: pyams-layer
Requires-Dist: pyams-security >=1.8.1
Requires-Dist: pyams-security-views
Requires-Dist: pyams-template
Requires-Dist: pyams-utils
Requires-Dist: pyramid >=2.0.0
Requires-Dist: zope.annotation
Requires-Dist: zope.container
Requires-Dist: zope.interface
Requires-Dist: zope.lifecycleevent
Requires-Dist: zope.schema
Requires-Dist: zope.traversing
Provides-Extra: test
Requires-Dist: pyams-site ; extra == 'test'
Requires-Dist: pyams-skin ; extra == 'test'
Requires-Dist: pyams-viewlet ; extra == 'test'
Requires-Dist: pyams-zmi ; extra == 'test'
Requires-Dist: pyramid-zcml ; extra == 'test'
Requires-Dist: zope.exceptions ; extra == 'test'
